odoo10_addon_l10n_fr_chorus_factur_x-10.0.1.0.0-py2.7-nspkg.pth
odoo/addons/l10n_fr_chorus_factur-x/README.rst
odoo/addons/l10n_fr_chorus_factur-x/__init__.py
odoo/addons/l10n_fr_chorus_factur-x/__manifest__.py
odoo/addons/l10n_fr_chorus_factur-x/models/.ubl.py.swo
odoo/addons/l10n_fr_chorus_factur-x/models/__init__.py
odoo/addons/l10n_fr_chorus_factur-x/models/account_invoice.py
odoo10_addon_l10n_fr_chorus_factur_x-10.0.1.0.0.dist-info/DESCRIPTION.rst
odoo10_addon_l10n_fr_chorus_factur_x-10.0.1.0.0.dist-info/METADATA
odoo10_addon_l10n_fr_chorus_factur_x-10.0.1.0.0.dist-info/RECORD
odoo10_addon_l10n_fr_chorus_factur_x-10.0.1.0.0.dist-info/WHEEL
odoo10_addon_l10n_fr_chorus_factur_x-10.0.1.0.0.dist-info/metadata.json
odoo10_addon_l10n_fr_chorus_factur_x-10.0.1.0.0.dist-info/namespace_packages.txt
odoo10_addon_l10n_fr_chorus_factur_x-10.0.1.0.0.dist-info/top_level.txt
